{"id": 10190, "input_str": " The Walton siblings from left, Alice Walton, Jim Walton and Wal-Mart Chairman Rob Walton, the children of the late Wal-Mart Stores Inc. founder Sam Walton, appear on stage during the company's annual shareholder meeting in Fayetteville, Arkansas, U.S., on Friday, June 3, 2011. Wal-Mart Stores Inc. renewed plans to buy back as much as $15 billion of its shares, potentially bolstering the Walton family's control of the world's largest retailer. Photographer: Beth", "correct_token_str": " Hall", "generated_token_strs": [" Wilkinson", "any", "any", " A", "any", "any", "any", "any", "any", "any", "anc", " Boh", "any", " Barker", "any", "any", "any", "any", "any", "any", "any", "any", " Pl", " Cont", " Harriet", "any", "any", "any", "any", "any", " Vog", "any", " Sh", " N", "any", "any", " Carson", " Wo", "any", "any", "any", "any", " Davis", " Bennett", "any", "any", " A", "any", " Han", "any", " Has", "any", " Knight", "any", "any", "any", "any", " Har", " Doe", " Wilkinson", " Jacob", "any", " Nielsen", "any", "any", "any", "any", " Kaplan", "any", " Burton", " Re", "any", " St", " Peters", " Grand", " Hab", " Ad", " Av", "ney", " Bart", "any", "any", " El", "leigh", " Chen", " Bec", " Wall", "any", " Har", "any", "any", "ke", " Loc", " Fried", " Warren", "any", "any", " Fletcher", "any", "any", "any", "any", "any", "any", " Jackson", " Hew", " Sch", "any", " Hansen", "any", "any", "any", " McDonald", "any", " Hill", "any", "any", "any", "any", "any", " Per", "any", "any", " Berger", "any", "any", "any", " V", "any", "any", "any", "anie", " Hel", "any", " Bar", " Smith", "any", " Israel", "any", " H", "any", "any", "any", "any", "any", " Christ", " Ch", " B", "any", "une", " Fish", "any", "any", " Vaughan", " Sh", "any", " Yang", "any", "any", "any", "any", " Fritz", " Walsh", " Bern", "any", " Ry", "any", " Collection", " A", "any", " Smith", "any", " Pl", "any", "any", "any", "any", " Scan", " Sv", "any", " Gl", " Becker", "any", "any", "any", " Myr", "any", " Schwartz", " Van", "any", "any", " Sal", "any", " Household", " Beh", " L", "any", "any", "any", " Bond", " Barrett", " Wen", "any", " Hel", "any", " Wright", " Bren", "any", "any", " Kaplan", "any", "any", "any", "any", "any", "any", "any", "any", "any", "any", " Freeman", "any", " St", " Ann", "any", " Ross", "any", " Troy", "any", " L", "any", " Sh", "any", "any", " Dow", " Riley", "any", " Gl", "any", "any", "an", "dem", " Taylor", " Din", " Jones", " Frey", "any", " Din", " Han", " Rosen", "any", "any", "any", " Smith", "any", " R", "any", "any", " Yang", "n", " J", " Ch", "any", " E", "any", "any", " Bu", " Hansen", "Sim", "any", "any", " Din", "any", "any", "any", " Reb", "any", " Thompson", "any", "any", "anie", " Sk", "any", "any", " Sw", "any", "any", "any", " Barrett", "any", "any", " Frey", "any", " Faul", " Stark", " Kaufman", "any", "any", "any", "any", " Mac", " N", "any", " J", "any", "any", "any", "any", "any", "anie", "any", "any", "any", "any", "any", "any", " Gill", "any", " Ku", "any", "any", "any", " Curry", "any", " A", "any", "any", " Ca", "any", "any", "any", "any", "any", "any", "une", "any", " Said", "any", "any", " Bry", "any", " Jones", "any", "any", "any", " Light", " J", "any", "any", "any", "any", "anna", " Smith", " Tro", "any", " Mid", " Beh", "any", " Freeman", " D", " Beh", "any", " Har", "any", " Sm", " Davis", "any", "any", "j", " Had", " Chart", "any", " Se", " A", "any", " A", " O", " Decl", " T", " Fog", " Tiff", "any", "any", "any", " Gross", " Fay", "any", " Pool", " Fort", " Warren", " Walsh", "any", "any", "any", "any", "any", " Am", " Peterson", " Nielsen", "any"], "generator_index": 1, "correct_logprobs": [-11.26613712310791, -6.582939147949219, -8.642903327941895], "generated_logprobss": [[-7.320733070373535, -5.714158058166504, -5.714158058166504, -8.042425155639648, -5.714158058166504, -5.714158058166504, -5.714158058166504, -5.714158058166504, -5.714158058166504, -5.714158058166504, -13.702585220336914, -11.859447479248047, -5.714158058166504, -10.294032096862793, -5.714158058166504, -5.714158058166504, -5.714158058166504, -5.714158058166504, -5.714158058166504, -5.714158058166504, -5.714158058166504, -5.714158058166504, -9.161031723022461, -14.33381462097168, -14.41052532196045, -5.714158058166504, -5.714158058166504, -5.714158058166504, -5.714158058166504, -5.714158058166504, -8.859308242797852, -5.714158058166504, -6.631401062011719, -5.794534683227539, -5.714158058166504, -5.714158058166504, -11.28334903717041, -10.756186485290527, -5.714158058166504, -5.714158058166504, -5.714158058166504, -5.714158058166504, -7.591269493103027, -12.86596965789795, -5.714158058166504, -5.714158058166504, -8.042425155639648, -5.714158058166504, -6.458708763122559, -5.714158058166504, -7.466480255126953, -5.714158058166504, -6.293615341186523, -5.714158058166504, -5.714158058166504, -5.714158058166504, -5.714158058166504, -9.597335815429688, -8.411396026611328, -7.320733070373535, -9.674395561218262, -5.714158058166504, -13.08820629119873, -5.714158058166504, -5.714158058166504, -5.714158058166504, -5.714158058166504, -7.979315757751465, -5.714158058166504, -7.9397478103637695, -8.578580856323242, -5.714158058166504, -6.905276298522949, -6.009108543395996, -10.701676368713379, -12.534393310546875, -8.946919441223145, -9.558300971984863, -10.45493221282959, -9.59687328338623, -5.714158058166504, -5.714158058166504, -8.717436790466309, -9.712227821350098, -9.795995712280273, -11.482867240905762, -11.228111267089844, -5.714158058166504, -9.597335815429688, -5.714158058166504, -5.714158058166504, -9.62034797668457, -12.269133567810059, -6.881628036499023, -12.712449073791504, -5.714158058166504, -5.714158058166504, -6.821491241455078, -5.714158058166504, -5.714158058166504, -5.714158058166504, -5.714158058166504, -5.714158058166504, -5.714158058166504, -7.758445739746094, -8.561244010925293, -6.135247230529785, -5.714158058166504, -9.008133888244629, -5.714158058166504, -5.714158058166504, -5.714158058166504, -9.558905601501465, -5.714158058166504, -11.5004243850708, -5.714158058166504, -5.714158058166504, -5.714158058166504, -5.714158058166504, -5.714158058166504, -11.145822525024414, -5.714158058166504, -5.714158058166504, -9.73952579498291, -5.714158058166504, -5.714158058166504, -5.714158058166504, -8.059325218200684, -5.714158058166504, -5.714158058166504, -5.714158058166504, -10.006272315979004, -4.840912818908691, -5.714158058166504, -9.701507568359375, -8.02979564666748, -5.714158058166504, -12.051941871643066, -5.714158058166504, -5.968840599060059, -5.714158058166504, -5.714158058166504, -5.714158058166504, -5.714158058166504, -5.714158058166504, -9.02546215057373, -8.032456398010254, -7.233189582824707, -5.714158058166504, -12.20149040222168, -8.652117729187012, -5.714158058166504, -5.714158058166504, -9.59131145477295, -6.631401062011719, -5.714158058166504, -9.477088928222656, -5.714158058166504, -5.714158058166504, -5.714158058166504, -5.714158058166504, -10.16909122467041, -8.32700252532959, -8.791027069091797, -5.714158058166504, -10.952205657958984, -5.714158058166504, -13.665828704833984, -8.042425155639648, -5.714158058166504, -8.02979564666748, -5.714158058166504, -9.161031723022461, -5.714158058166504, -5.714158058166504, -5.714158058166504, -5.714158058166504, -7.590025901794434, -13.328721046447754, -5.714158058166504, -10.169580459594727, -10.83767318725586, -5.714158058166504, -5.714158058166504, -5.714158058166504, -9.819714546203613, -5.714158058166504, -8.134483337402344, -8.336661338806152, -5.714158058166504, -5.714158058166504, -10.632367134094238, -5.714158058166504, -17.499773025512695, -8.663300514221191, -5.486615180969238, -5.714158058166504, -5.714158058166504, -5.714158058166504, -10.899109840393066, -10.218562126159668, -10.450865745544434, -5.714158058166504, -4.840912818908691, -5.714158058166504, -7.448413848876953, -8.01015853881836, -5.714158058166504, -5.714158058166504, -7.979315757751465, -5.714158058166504, -5.714158058166504, -5.714158058166504, -5.714158058166504, -5.714158058166504, -5.714158058166504, -5.714158058166504, -5.714158058166504, -5.714158058166504, -5.714158058166504, -7.748198509216309, -5.714158058166504, -6.905276298522949, -7.538548469543457, -5.714158058166504, -11.365095138549805, -5.714158058166504, -13.969244956970215, -5.714158058166504, -5.486615180969238, -5.714158058166504, -6.631401062011719, -5.714158058166504, -5.714158058166504, -12.17562484741211, -5.42542839050293, -5.714158058166504, -10.169580459594727, -5.714158058166504, -5.714158058166504, -9.512768745422363, -12.703608512878418, -5.824361801147461, -12.264060020446777, -7.9726762771606445, -11.915289878845215, -5.714158058166504, -12.264060020446777, -6.458708763122559, -9.984560012817383, -5.714158058166504, -5.714158058166504, -5.714158058166504, -8.02979564666748, -5.714158058166504, -5.727372169494629, -5.714158058166504, -5.714158058166504, -9.477088928222656, -8.385586738586426, -6.907412528991699, -8.032456398010254, -5.714158058166504, -7.716554641723633, -5.714158058166504, -5.714158058166504, -9.645358085632324, -9.008133888244629, -12.18431568145752, -5.714158058166504, -5.714158058166504, -12.264060020446777, -5.714158058166504, -5.714158058166504, -5.714158058166504, -12.031196594238281, -5.714158058166504, -9.104018211364746, -5.714158058166504, -5.714158058166504, -10.006272315979004, -10.541085243225098, -5.714158058166504, -5.714158058166504, -9.43482494354248, -5.714158058166504, -5.714158058166504, -5.714158058166504, -10.218562126159668, -5.714158058166504, -5.714158058166504, -11.915289878845215, -5.714158058166504, -9.717453956604004, -11.70436954498291, -10.040539741516113, -5.714158058166504, -5.714158058166504, -5.714158058166504, -5.714158058166504, -7.2556304931640625, -5.794534683227539, -5.714158058166504, -6.907412528991699, -5.714158058166504, -5.714158058166504, -5.714158058166504, -5.714158058166504, -5.714158058166504, -10.006272315979004, -5.714158058166504, -5.714158058166504, -5.714158058166504, -5.714158058166504, -5.714158058166504, -5.714158058166504, -11.796723365783691, -5.714158058166504, -12.319233894348145, -5.714158058166504, -5.714158058166504, -5.714158058166504, -5.008571624755859, -5.714158058166504, -8.042425155639648, -5.714158058166504, -5.714158058166504, -10.328680038452148, -5.714158058166504, -5.714158058166504, -5.714158058166504, -5.714158058166504, -5.714158058166504, -5.714158058166504, -12.20149040222168, -5.714158058166504, -11.715222358703613, -5.714158058166504, -5.714158058166504, -9.103069305419922, -5.714158058166504, -7.9726762771606445, -5.714158058166504, -5.714158058166504, -5.714158058166504, -12.61190128326416, -6.907412528991699, -5.714158058166504, -5.714158058166504, -5.714158058166504, -5.714158058166504, -4.012808799743652, -8.02979564666748, -10.46889877319336, -5.714158058166504, -11.668036460876465, -8.663300514221191, -5.714158058166504, -7.748198509216309, -5.177057266235352, -8.663300514221191, -5.714158058166504, -9.597335815429688, -5.714158058166504, -10.148648262023926, -7.591269493103027, -5.714158058166504, -5.714158058166504, -10.830259323120117, -8.938850402832031, -15.591158866882324, -5.714158058166504, -9.590886116027832, -8.042425155639648, -5.714158058166504, -8.042425155639648, -6.954741477966309, -14.803457260131836, -7.642610549926758, -13.20685863494873, -10.051383972167969, -5.714158058166504, -5.714158058166504, -5.714158058166504, -10.961470603942871, -10.549625396728516, -5.714158058166504, -12.762171745300293, -9.342293739318848, -12.712449073791504, -8.32700252532959, -5.714158058166504, -5.714158058166504, -5.714158058166504, -5.714158058166504, -5.714158058166504, -6.008702278137207, -7.327497482299805, -13.08820629119873, -5.714158058166504], [-4.948673248291016, -0.5697252154350281, -0.5697252154350281, -4.959526062011719, -0.5697252154350281, -0.5697252154350281, -0.5697252154350281, -0.5697252154350281, -0.5697252154350281, -0.5697252154350281, -7.266242980957031, -8.782562255859375, -0.5697252154350281, -9.311874389648438, -0.5697252154350281, -0.5697252154350281, -0.5697252154350281, -0.5697252154350281, -0.5697252154350281, -0.5697252154350281, -0.5697252154350281, -0.5697252154350281, -7.114723205566406, -9.619880676269531, -14.134262084960938, -0.5697252154350281, -0.5697252154350281, -0.5697252154350281, -0.5697252154350281, -0.5697252154350281, -9.548721313476562, -0.5697252154350281, -5.443813323974609, -6.179073333740234, -0.5697252154350281, -0.5697252154350281, -6.643669128417969, -9.337005615234375, -0.5697252154350281, -0.5697252154350281, -0.5697252154350281, -0.5697252154350281, -7.660144805908203, -8.143619537353516, -0.5697252154350281, -0.5697252154350281, -4.959526062011719, -0.5697252154350281, -6.334556579589844, -0.5697252154350281, -8.572025299072266, -0.5697252154350281, -8.43682861328125, -0.5697252154350281, -0.5697252154350281, -0.5697252154350281, -0.5697252154350281, -4.803379058837891, -11.696006774902344, -4.948673248291016, -7.065376281738281, -0.5697252154350281, -7.976631164550781, -0.5697252154350281, -0.5697252154350281, -0.5697252154350281, -0.5697252154350281, -6.745475769042969, -0.5697252154350281, -7.614356994628906, -7.406219482421875, -0.5697252154350281, -5.664630889892578, -9.2877197265625, -11.505928039550781, -7.469688415527344, -8.832206726074219, -10.111900329589844, -7.612907409667969, -8.066215515136719, -0.5697252154350281, -0.5697252154350281, -7.469383239746094, -11.251834869384766, -9.762367248535156, -8.407028198242188, -7.464282989501953, -0.5697252154350281, -4.803379058837891, -0.5697252154350281, -0.5697252154350281, -5.7724456787109375, -10.57135009765625, -8.407337188720703, -5.8102569580078125, -0.5697252154350281, -0.5697252154350281, -8.208747863769531, -0.5697252154350281, -0.5697252154350281, -0.5697252154350281, -0.5697252154350281, -0.5697252154350281, -0.5697252154350281, -6.7338104248046875, -8.582637786865234, -6.223724365234375, -0.5697252154350281, -7.279384613037109, -0.5697252154350281, -0.5697252154350281, -0.5697252154350281, -9.309120178222656, -0.5697252154350281, -7.532932281494141, -0.5697252154350281, -0.5697252154350281, -0.5697252154350281, -0.5697252154350281, -0.5697252154350281, -7.239082336425781, -0.5697252154350281, -0.5697252154350281, -7.606330871582031, -0.5697252154350281, -0.5697252154350281, -0.5697252154350281, -6.765140533447266, -0.5697252154350281, -0.5697252154350281, -0.5697252154350281, -6.339576721191406, -6.373401641845703, -0.5697252154350281, -6.947429656982422, -6.511756896972656, -0.5697252154350281, -5.8046417236328125, -0.5697252154350281, -6.783790588378906, -0.5697252154350281, -0.5697252154350281, -0.5697252154350281, -0.5697252154350281, -0.5697252154350281, -9.403751373291016, -6.697113037109375, -6.717498779296875, -0.5697252154350281, -5.743049621582031, -9.16238021850586, -0.5697252154350281, -0.5697252154350281, -8.06439208984375, -5.443813323974609, -0.5697252154350281, -8.406562805175781, -0.5697252154350281, -0.5697252154350281, -0.5697252154350281, -0.5697252154350281, -8.688018798828125, -8.284931182861328, -8.708938598632812, -0.5697252154350281, -11.737037658691406, -0.5697252154350281, -12.128715515136719, -4.959526062011719, -0.5697252154350281, -6.511756896972656, -0.5697252154350281, -7.114723205566406, -0.5697252154350281, -0.5697252154350281, -0.5697252154350281, -0.5697252154350281, -9.39947509765625, -8.553306579589844, -0.5697252154350281, -6.368473052978516, -6.232784271240234, -0.5697252154350281, -0.5697252154350281, -0.5697252154350281, -9.841400146484375, -0.5697252154350281, -7.199436187744141, -7.506462097167969, -0.5697252154350281, -0.5697252154350281, -7.520496368408203, -0.5697252154350281, -12.730461120605469, -4.843662261962891, -6.372810363769531, -0.5697252154350281, -0.5697252154350281, -0.5697252154350281, -8.566062927246094, -7.076053619384766, -6.5536041259765625, -0.5697252154350281, -6.373401641845703, -0.5697252154350281, -7.7308502197265625, -8.532745361328125, -0.5697252154350281, -0.5697252154350281, -6.745475769042969, -0.5697252154350281, -0.5697252154350281, -0.5697252154350281, -0.5697252154350281, -0.5697252154350281, -0.5697252154350281, -0.5697252154350281, -0.5697252154350281, -0.5697252154350281, -0.5697252154350281, -8.948921203613281, -0.5697252154350281, -5.664630889892578, -6.054233551025391, -0.5697252154350281, -8.316001892089844, -0.5697252154350281, -10.891334533691406, -0.5697252154350281, -6.372810363769531, -0.5697252154350281, -5.443813323974609, -0.5697252154350281, -0.5697252154350281, -9.121360778808594, -5.864128112792969, -0.5697252154350281, -6.368473052978516, -0.5697252154350281, -0.5697252154350281, -5.978919982910156, -13.891536712646484, -6.560462951660156, -6.415840148925781, -5.6221466064453125, -7.8824310302734375, -0.5697252154350281, -6.415840148925781, -6.334556579589844, -7.489307403564453, -0.5697252154350281, -0.5697252154350281, -0.5697252154350281, -6.511756896972656, -0.5697252154350281, -5.999626159667969, -0.5697252154350281, -0.5697252154350281, -8.406562805175781, -7.427215576171875, -5.174411773681641, -6.697113037109375, -0.5697252154350281, -6.497047424316406, -0.5697252154350281, -0.5697252154350281, -8.214866638183594, -7.279384613037109, -12.695411682128906, -0.5697252154350281, -0.5697252154350281, -6.415840148925781, -0.5697252154350281, -0.5697252154350281, -0.5697252154350281, -8.861152648925781, -0.5697252154350281, -6.3771209716796875, -0.5697252154350281, -0.5697252154350281, -6.339576721191406, -8.105384826660156, -0.5697252154350281, -0.5697252154350281, -7.8597259521484375, -0.5697252154350281, -0.5697252154350281, -0.5697252154350281, -7.076053619384766, -0.5697252154350281, -0.5697252154350281, -7.8824310302734375, -0.5697252154350281, -10.326419830322266, -9.39141845703125, -7.961631774902344, -0.5697252154350281, -0.5697252154350281, -0.5697252154350281, -0.5697252154350281, -7.470470428466797, -6.179073333740234, -0.5697252154350281, -5.174411773681641, -0.5697252154350281, -0.5697252154350281, -0.5697252154350281, -0.5697252154350281, -0.5697252154350281, -6.339576721191406, -0.5697252154350281, -0.5697252154350281, -0.5697252154350281, -0.5697252154350281, -0.5697252154350281, -0.5697252154350281, -7.6165008544921875, -0.5697252154350281, -8.375434875488281, -0.5697252154350281, -0.5697252154350281, -0.5697252154350281, -8.002593994140625, -0.5697252154350281, -4.959526062011719, -0.5697252154350281, -0.5697252154350281, -7.207939147949219, -0.5697252154350281, -0.5697252154350281, -0.5697252154350281, -0.5697252154350281, -0.5697252154350281, -0.5697252154350281, -5.743049621582031, -0.5697252154350281, -10.760746002197266, -0.5697252154350281, -0.5697252154350281, -9.157146453857422, -0.5697252154350281, -5.6221466064453125, -0.5697252154350281, -0.5697252154350281, -0.5697252154350281, -8.316360473632812, -5.174411773681641, -0.5697252154350281, -0.5697252154350281, -0.5697252154350281, -0.5697252154350281, -6.996986389160156, -6.511756896972656, -8.770511627197266, -0.5697252154350281, -11.205177307128906, -4.843662261962891, -0.5697252154350281, -8.948921203613281, -6.105842590332031, -4.843662261962891, -0.5697252154350281, -4.803379058837891, -0.5697252154350281, -8.62472915649414, -7.660144805908203, -0.5697252154350281, -0.5697252154350281, -7.9440460205078125, -6.467720031738281, -8.052532196044922, -0.5697252154350281, -7.651451110839844, -4.959526062011719, -0.5697252154350281, -4.959526062011719, -6.869911193847656, -11.527061462402344, -6.798927307128906, -10.955387115478516, -11.013153076171875, -0.5697252154350281, -0.5697252154350281, -0.5697252154350281, -7.6955718994140625, -9.506500244140625, -0.5697252154350281, -8.873733520507812, -10.075157165527344, -5.8102569580078125, -8.284931182861328, -0.5697252154350281, -0.5697252154350281, -0.5697252154350281, -0.5697252154350281, -0.5697252154350281, -7.870296478271484, -6.518402099609375, -7.976631164550781, -0.5697252154350281], [-4.590954780578613, -2.6942265033721924, -2.6942265033721924, -4.072426795959473, -2.6942265033721924, -2.6942265033721924, -2.6942265033721924, -2.6942265033721924, -2.6942265033721924, -2.6942265033721924, -7.76693058013916, -10.404107093811035, -2.6942265033721924, -9.108704566955566, -2.6942265033721924, -2.6942265033721924, -2.6942265033721924, -2.6942265033721924, -2.6942265033721924, -2.6942265033721924, -2.6942265033721924, -2.6942265033721924, -9.582039833068848, -8.520890235900879, -12.413025856018066, -2.6942265033721924, -2.6942265033721924, -2.6942265033721924, -2.6942265033721924, -2.6942265033721924, -8.527642250061035, -2.6942265033721924, -5.202801704406738, -8.442017555236816, -2.6942265033721924, -2.6942265033721924, -10.47258472442627, -11.952893257141113, -2.6942265033721924, -2.6942265033721924, -2.6942265033721924, -2.6942265033721924, -8.42958927154541, -9.939637184143066, -2.6942265033721924, -2.6942265033721924, -4.072426795959473, -2.6942265033721924, -6.866028785705566, -2.6942265033721924, -12.246373176574707, -2.6942265033721924, -11.808289527893066, -2.6942265033721924, -2.6942265033721924, -2.6942265033721924, -2.6942265033721924, -5.074475288391113, -7.989560127258301, -4.590954780578613, -8.411725044250488, -2.6942265033721924, -8.781960487365723, -2.6942265033721924, -2.6942265033721924, -2.6942265033721924, -2.6942265033721924, -9.156441688537598, -2.6942265033721924, -9.97899341583252, -4.76882266998291, -2.6942265033721924, -7.016644477844238, -10.315545082092285, -12.7153902053833, -11.415215492248535, -7.123970985412598, -12.262158393859863, -12.935505867004395, -3.8361141681671143, -2.6942265033721924, -2.6942265033721924, -6.954239845275879, -10.673710823059082, -10.125809669494629, -14.794793128967285, -9.570809364318848, -2.6942265033721924, -5.074475288391113, -2.6942265033721924, -2.6942265033721924, -8.002854347229004, -10.92357349395752, -10.058541297912598, -5.014958381652832, -2.6942265033721924, -2.6942265033721924, -8.260178565979004, -2.6942265033721924, -2.6942265033721924, -2.6942265033721924, -2.6942265033721924, -2.6942265033721924, -2.6942265033721924, -5.615887641906738, -8.716618537902832, -6.477368354797363, -2.6942265033721924, -9.457066535949707, -2.6942265033721924, -2.6942265033721924, -2.6942265033721924, -9.172272682189941, -2.6942265033721924, -7.565445899963379, -2.6942265033721924, -2.6942265033721924, -2.6942265033721924, -2.6942265033721924, -2.6942265033721924, -10.31713581085205, -2.6942265033721924, -2.6942265033721924, -10.953381538391113, -2.6942265033721924, -2.6942265033721924, -2.6942265033721924, -9.072819709777832, -2.6942265033721924, -2.6942265033721924, -2.6942265033721924, -8.392022132873535, -5.870846748352051, -2.6942265033721924, -8.039116859436035, -8.291924476623535, -2.6942265033721924, -4.940030097961426, -2.6942265033721924, -6.616997718811035, -2.6942265033721924, -2.6942265033721924, -2.6942265033721924, -2.6942265033721924, -2.6942265033721924, -5.892159461975098, -7.630669593811035, -5.671753883361816, -2.6942265033721924, -7.348954200744629, -10.8190279006958, -2.6942265033721924, -2.6942265033721924, -12.816338539123535, -5.202801704406738, -2.6942265033721924, -10.305306434631348, -2.6942265033721924, -2.6942265033721924, -2.6942265033721924, -2.6942265033721924, -9.713215827941895, -5.565644264221191, -10.914315223693848, -2.6942265033721924, -6.097290992736816, -2.6942265033721924, -15.491856575012207, -4.072426795959473, -2.6942265033721924, -8.291924476623535, -2.6942265033721924, -9.582039833068848, -2.6942265033721924, -2.6942265033721924, -2.6942265033721924, -2.6942265033721924, -12.392743110656738, -8.9619722366333, -2.6942265033721924, -7.299538612365723, -8.1740083694458, -2.6942265033721924, -2.6942265033721924, -2.6942265033721924, -10.777623176574707, -2.6942265033721924, -9.464425086975098, -4.846306800842285, -2.6942265033721924, -2.6942265033721924, -7.399415016174316, -2.6942265033721924, -17.404394149780273, -3.477383852005005, -2.9975712299346924, -2.6942265033721924, -2.6942265033721924, -2.6942265033721924, -8.988038063049316, -13.262211799621582, -7.138527870178223, -2.6942265033721924, -5.870846748352051, -2.6942265033721924, -9.108654975891113, -11.36131763458252, -2.6942265033721924, -2.6942265033721924, -9.156441688537598, -2.6942265033721924, -2.6942265033721924, -2.6942265033721924, -2.6942265033721924, -2.6942265033721924, -2.6942265033721924, -2.6942265033721924, -2.6942265033721924, -2.6942265033721924, -2.6942265033721924, -9.841954231262207, -2.6942265033721924, -7.016644477844238, -5.099888801574707, -2.6942265033721924, -8.848809242248535, -2.6942265033721924, -12.17171573638916, -2.6942265033721924, -2.9975712299346924, -2.6942265033721924, -5.202801704406738, -2.6942265033721924, -2.6942265033721924, -12.018509864807129, -7.654335975646973, -2.6942265033721924, -7.299538612365723, -2.6942265033721924, -2.6942265033721924, -7.0486040115356445, -15.699967384338379, -8.167309761047363, -7.446049690246582, -7.873093605041504, -4.553338050842285, -2.6942265033721924, -7.446049690246582, -6.866028785705566, -9.6827974319458, -2.6942265033721924, -2.6942265033721924, -2.6942265033721924, -8.291924476623535, -2.6942265033721924, -4.375851631164551, -2.6942265033721924, -2.6942265033721924, -10.305306434631348, -9.465638160705566, -5.713799476623535, -7.630669593811035, -2.6942265033721924, -7.233529090881348, -2.6942265033721924, -2.6942265033721924, -8.525113105773926, -9.457066535949707, -11.634758949279785, -2.6942265033721924, -2.6942265033721924, -7.446049690246582, -2.6942265033721924, -2.6942265033721924, -2.6942265033721924, -11.503193855285645, -2.6942265033721924, -7.397690773010254, -2.6942265033721924, -2.6942265033721924, -8.392022132873535, -7.284798622131348, -2.6942265033721924, -2.6942265033721924, -8.026688575744629, -2.6942265033721924, -2.6942265033721924, -2.6942265033721924, -13.262211799621582, -2.6942265033721924, -2.6942265033721924, -4.553338050842285, -2.6942265033721924, -11.336209297180176, -13.442898750305176, -9.30443286895752, -2.6942265033721924, -2.6942265033721924, -2.6942265033721924, -2.6942265033721924, -8.03701114654541, -8.442017555236816, -2.6942265033721924, -5.713799476623535, -2.6942265033721924, -2.6942265033721924, -2.6942265033721924, -2.6942265033721924, -2.6942265033721924, -8.392022132873535, -2.6942265033721924, -2.6942265033721924, -2.6942265033721924, -2.6942265033721924, -2.6942265033721924, -2.6942265033721924, -7.417515754699707, -2.6942265033721924, -6.7047624588012695, -2.6942265033721924, -2.6942265033721924, -2.6942265033721924, -7.814438819885254, -2.6942265033721924, -4.072426795959473, -2.6942265033721924, -2.6942265033721924, -9.866776466369629, -2.6942265033721924, -2.6942265033721924, -2.6942265033721924, -2.6942265033721924, -2.6942265033721924, -2.6942265033721924, -7.348954200744629, -2.6942265033721924, -8.993515968322754, -2.6942265033721924, -2.6942265033721924, -11.373444557189941, -2.6942265033721924, -7.873093605041504, -2.6942265033721924, -2.6942265033721924, -2.6942265033721924, -9.849213600158691, -5.713799476623535, -2.6942265033721924, -2.6942265033721924, -2.6942265033721924, -2.6942265033721924, -11.805573463439941, -8.291924476623535, -10.61299991607666, -2.6942265033721924, -12.884381294250488, -3.477383852005005, -2.6942265033721924, -9.841954231262207, -3.945725679397583, -3.477383852005005, -2.6942265033721924, -5.074475288391113, -2.6942265033721924, -10.860943794250488, -8.42958927154541, -2.6942265033721924, -2.6942265033721924, -11.390839576721191, -10.4169282913208, -11.541962623596191, -2.6942265033721924, -8.425976753234863, -4.072426795959473, -2.6942265033721924, -4.072426795959473, -9.489350318908691, -14.493435859680176, -6.673195838928223, -11.380105018615723, -15.150567054748535, -2.6942265033721924, -2.6942265033721924, -2.6942265033721924, -7.364022254943848, -8.488556861877441, -2.6942265033721924, -11.052872657775879, -12.802495002746582, -5.014958381652832, -5.565644264221191, -2.6942265033721924, -2.6942265033721924, -2.6942265033721924, -2.6942265033721924, -2.6942265033721924, -8.516793251037598, -8.800393104553223, -8.781960487365723, -2.6942265033721924]], "generation_probs": [0.007092813029885292, 0.5656808614730835, 0.5656808614730835, 0.007016252260655165, 0.5656808614730835, 0.5656808614730835, 0.5656808614730835, 0.5656808614730835, 0.5656808614730835, 0.5656808614730835, 0.0006987322121858597, 0.00015338457887992263, 0.5656808614730835, 9.034503455040976e-05, 0.5656808614730835, 0.5656808614730835, 0.5656808614730835, 0.5656808614730835, 0.5656808614730835, 0.5656808614730835, 0.5656808614730835, 0.5656808614730835, 0.0008130457135848701, 6.63955433992669e-05, 7.270560899996781e-07, 0.5656808614730835, 0.5656808614730835, 0.5656808614730835, 0.5656808614730835, 0.5656808614730835, 7.129236473701894e-05, 0.5656808614730835, 0.004322967026382685, 0.002072347328066826, 0.5656808614730835, 0.5656808614730835, 0.0013022402999922633, 8.810285362415016e-05, 0.5656808614730835, 0.5656808614730835, 0.5656808614730835, 0.5656808614730835, 0.0004712391528300941, 0.00029058349900878966, 0.5656808614730835, 0.5656808614730835, 0.007016252260655165, 0.5656808614730835, 0.001773932366631925, 0.5656808614730835, 0.0001893288135761395, 0.5656808614730835, 0.00021673641458619386, 0.5656808614730835, 0.5656808614730835, 0.5656808614730835, 0.5656808614730835, 0.008201985619962215, 8.327004252350889e-06, 0.007092813029885292, 0.0008541734423488379, 0.5656808614730835, 0.0003433943202253431, 0.5656808614730835, 0.5656808614730835, 0.5656808614730835, 0.5656808614730835, 0.0011761889327317476, 0.5656808614730835, 0.0004933177842758596, 0.0006074628909118474, 0.5656808614730835, 0.003466427093371749, 9.255386976292357e-05, 1.0070220014313236e-05, 0.0005701059126295149, 0.00014595581160392612, 4.059359343955293e-05, 0.0004940333892591298, 0.000313969241688028, 0.5656808614730835, 0.5656808614730835, 0.0005702798953279853, 1.2983453416381963e-05, 5.757815597462468e-05, 0.0002232924452982843, 0.0005731959245167673, 0.5656808614730835, 0.008201985619962215, 0.5656808614730835, 0.5656808614730835, 0.0031121368519961834, 2.564017631812021e-05, 0.00022322346922010183, 0.0029966600704938173, 0.5656808614730835, 0.5656808614730835, 0.00027226144447922707, 0.5656808614730835, 0.5656808614730835, 0.5656808614730835, 0.5656808614730835, 0.5656808614730835, 0.5656808614730835, 0.001189989852719009, 0.00018733016622718424, 0.001981850480660796, 0.5656808614730835, 0.0006896097911521792, 0.5656808614730835, 0.5656808614730835, 0.5656808614730835, 9.059420699486509e-05, 0.5656808614730835, 0.0005351667059585452, 0.5656808614730835, 0.5656808614730835, 0.5656808614730835, 0.5656808614730835, 0.5656808614730835, 0.000717970309779048, 0.5656808614730835, 0.5656808614730835, 0.0004972931346856058, 0.5656808614730835, 0.5656808614730835, 0.5656808614730835, 0.0011532853823155165, 0.5656808614730835, 0.5656808614730835, 0.5656808614730835, 0.001765049179084599, 0.001706344890408218, 0.5656808614730835, 0.0009611023706384003, 0.0014858668437227607, 0.5656808614730835, 0.0030135340057313442, 0.5656808614730835, 0.0011319759069010615, 0.5656808614730835, 0.5656808614730835, 0.5656808614730835, 0.5656808614730835, 0.5656808614730835, 8.241431351052597e-05, 0.001234470633789897, 0.0012095598503947258, 0.5656808614730835, 0.003204979468137026, 0.00010491288412595168, 0.5656808614730835, 0.5656808614730835, 0.0003145422670058906, 0.004322967026382685, 0.5656808614730835, 0.00022339641873259097, 0.5656808614730835, 0.5656808614730835, 0.5656808614730835, 0.5656808614730835, 0.0001685937022557482, 0.00025229001767002046, 0.00016510339628439397, 0.5656808614730835, 7.992254722921643e-06, 0.5656808614730835, 5.4021393225411884e-06, 0.007016252260655165, 0.5656808614730835, 0.0014858668437227607, 0.5656808614730835, 0.0008130457135848701, 0.5656808614730835, 0.5656808614730835, 0.5656808614730835, 0.5656808614730835, 8.276750304503366e-05, 0.0001929061982082203, 0.5656808614730835, 0.0017147755715996027, 0.001963975839316845, 0.5656808614730835, 0.5656808614730835, 0.5656808614730835, 5.3202769777271897e-05, 0.5656808614730835, 0.0007470068521797657, 0.0005495218210853636, 0.5656808614730835, 0.5656808614730835, 0.0005418635555543005, 0.5656808614730835, 2.959586254291935e-06, 0.007878148928284645, 0.0017073543276637793, 0.5656808614730835, 0.5656808614730835, 0.5656808614730835, 0.0001904610253404826, 0.0008451016619801521, 0.0014249704545363784, 0.5656808614730835, 0.001706344890408218, 0.5656808614730835, 0.0004390706308186054, 0.00019691363559104502, 0.5656808614730835, 0.5656808614730835, 0.0011761889327317476, 0.5656808614730835, 0.5656808614730835, 0.5656808614730835, 0.5656808614730835, 0.5656808614730835, 0.5656808614730835, 0.5656808614730835, 0.5656808614730835, 0.5656808614730835, 0.5656808614730835, 0.0001298771967412904, 0.5656808614730835, 0.003466427093371749, 0.0023479009978473186, 0.5656808614730835, 0.0002445717400405556, 0.5656808614730835, 1.861887903942261e-05, 0.5656808614730835, 0.0017073543276637793, 0.5656808614730835, 0.004322967026382685, 0.5656808614730835, 0.5656808614730835, 0.0001093058381229639, 0.002839497523382306, 0.5656808614730835, 0.0017147755715996027, 0.5656808614730835, 0.5656808614730835, 0.0025315589737147093, 9.267919836020155e-07, 0.0014152303338050842, 0.0016354452818632126, 0.0036168687511235476, 0.0003773146599996835, 0.5656808614730835, 0.0016354452818632126, 0.001773932366631925, 0.0005590299842879176, 0.5656808614730835, 0.5656808614730835, 0.5656808614730835, 0.0014858668437227607, 0.5656808614730835, 0.0024796791840344667, 0.5656808614730835, 0.5656808614730835, 0.00022339641873259097, 0.0005948414909653366, 0.005659544840455055, 0.001234470633789897, 0.5656808614730835, 0.0015078847063705325, 0.5656808614730835, 0.5656808614730835, 0.0002706006052903831, 0.0006896097911521792, 3.0651569886686048e-06, 0.5656808614730835, 0.5656808614730835, 0.0016354452818632126, 0.5656808614730835, 0.5656808614730835, 0.5656808614730835, 0.00014179153367877007, 0.5656808614730835, 0.001700010383501649, 0.5656808614730835, 0.5656808614730835, 0.001765049179084599, 0.0003019090218003839, 0.5656808614730835, 0.5656808614730835, 0.000385979627026245, 0.5656808614730835, 0.5656808614730835, 0.5656808614730835, 0.0008451016619801521, 0.5656808614730835, 0.5656808614730835, 0.0003773146599996835, 0.5656808614730835, 3.275615017628297e-05, 8.34370221127756e-05, 0.0003485838242340833, 0.5656808614730835, 0.5656808614730835, 0.5656808614730835, 0.5656808614730835, 0.0005696602747775614, 0.002072347328066826, 0.5656808614730835, 0.005659544840455055, 0.5656808614730835, 0.5656808614730835, 0.5656808614730835, 0.5656808614730835, 0.5656808614730835, 0.001765049179084599, 0.5656808614730835, 0.5656808614730835, 0.5656808614730835, 0.5656808614730835, 0.5656808614730835, 0.5656808614730835, 0.0004922613734379411, 0.5656808614730835, 0.00023045962734613568, 0.5656808614730835, 0.5656808614730835, 0.5656808614730835, 0.0003345935547258705, 0.5656808614730835, 0.007016252260655165, 0.5656808614730835, 0.5656808614730835, 0.0007406820077449083, 0.5656808614730835, 0.5656808614730835, 0.5656808614730835, 0.5656808614730835, 0.5656808614730835, 0.5656808614730835, 0.003204979468137026, 0.5656808614730835, 2.121619036188349e-05, 0.5656808614730835, 0.5656808614730835, 0.00010546341218287125, 0.5656808614730835, 0.0036168687511235476, 0.5656808614730835, 0.5656808614730835, 0.5656808614730835, 0.00024448405019938946, 0.005659544840455055, 0.5656808614730835, 0.5656808614730835, 0.5656808614730835, 0.5656808614730835, 0.0009146340889856219, 0.0014858668437227607, 0.00015524413902312517, 0.5656808614730835, 1.3603584193333518e-05, 0.007878148928284645, 0.5656808614730835, 0.0001298771967412904, 0.0022298016119748354, 0.007878148928284645, 0.5656808614730835, 0.008201985619962215, 0.5656808614730835, 0.00017960883269552141, 0.0004712391528300941, 0.5656808614730835, 0.5656808614730835, 0.0003547681262716651, 0.001552761998027563, 0.0003182949440088123, 0.5656808614730835, 0.00047535382327623665, 0.007016252260655165, 0.5656808614730835, 0.007016252260655165, 0.0010385692585259676, 9.859633792075329e-06, 0.001114970538765192, 1.746368252497632e-05, 1.6483461877214722e-05, 0.5656808614730835, 0.5656808614730835, 0.5656808614730835, 0.00045483678695745766, 7.436685700668022e-05, 0.5656808614730835, 0.00014001883391756564, 4.2112871597055346e-05, 0.0029966600704938173, 0.00025229001767002046, 0.5656808614730835, 0.5656808614730835, 0.5656808614730835, 0.5656808614730835, 0.5656808614730835, 0.0003819210978690535, 0.0014760256744921207, 0.0003433943202253431, 0.5656808614730835], "generator_names": ["gelu_two_layers/", "gelu_twelve_layers/", "gelu_twenty_four_layers/"]}